<?xml version="1.0" encoding="utf-8"?>
<I c="Client_CASThumbnailCamera" i="camera" m="camera.Client_CASThumbnailCamera" n="uuCASPart_TattooHead_yuTattoo_HeadEP18ZygomaticLeft_AnchorWhite" s="5175662201023280691">
  <U n="CameraPosition">
    <T n="x">0.480066806077957</T>
    <T n="y">1.6651554107666</T>
    <T n="z">0.838159620761871</T>
  </U>
  <U n="TargetPosition">
    <T n="x">-0.0109457429498434</T>
    <T n="y">1.71953058242798</T>
    <T n="z">0.00643114978447556</T>
  </U>
  <T n="CameraFOV">10</T>
</I>