<?xml version="1.0" encoding="utf-8"?>
<I c="TestSetInstance" i="snippet" m="event_testing.tests" n="testSetInstance_InteractionIsEncouragedByClubOrCustomerRulesOrHobbyClass" s="126907">
  <L n="test">
    <L>
      <V t="club_test">
        <U n="club_test">
          <V n="affordance_rule" t="enabled">
            <V n="enabled" t="is_encouraged" />
          </V>
          <V n="club" t="use_any_club" />
        </U>
      </V>
    </L>
    <L>
      <V t="small_business_is_affordance_encouraged_test">
        <U n="small_business_is_affordance_encouraged_test">
          <E n="small_business_customer_situation_tag">Situation_SmallBusiness_Customer</E>
          <V n="tooltip" t="disabled" />
        </U>
      </V>
    </L>
    <L>
      <V t="situation_job_test">
        <U n="situation_job_test">
          <L n="role_tags">
            <E>Role_HobbyClass_Attendee</E>
          </L>
        </U>
      </V>
    </L>
  </L>
</I>