<?xml version="1.0" encoding="utf-8"?>
<I c="TestSetInstance" i="snippet" m="event_testing.tests" n="testSetInstance_EmotionVeryNegative_MoodBuffs_Actor" s="380762">
  <L n="test">
    <L>
      <V t="buff">
        <U n="buff">
          <V n="whitelist" t="enabled">
            <L n="enabled">
              <T>12840<!--MoodBuff_Hidden_Enraged--></T>
              <T>12827<!--MoodBuff_Hidden_Furious--></T>
              <T>27323<!--MoodBuff_Hidden_HotHead2--></T>
              <T>27320<!--MoodBuff_Hidden_HotHead3--></T>
              <T>12842<!--MoodBuff_Hidden_Humiliated--></T>
              <T>12848<!--MoodBuff_Hidden_Mortified--></T>
              <T>12832<!--MoodBuff_Hidden_Depressed--></T>
              <T>27155<!--MoodBuff_Hidden_Gloomier--></T>
              <T>12856<!--MoodBuff_Hidden_Stressed--></T>
              <T>12847<!--MoodBuff_Hidden_Miserable--></T>
              <T>251723<!--moodBuffs_Hidden_ScaredTrack_Terrified--></T>
            </L>
          </V>
        </U>
      </V>
    </L>
  </L>
</I>