<?xml version="1.0" encoding="utf-8"?>
<I c="AttractionPreferenceItem" i="cas_preference_item" m="cas.cas_preference_item" n="preferenceItem_Attraction_Characteristics_Pessimistic" s="363898">
  <T n="cas_preference_category">363385<!--PreferenceCategory_Attraction_Characteristics--></T>
  <T n="dislike">363952<!--trait_Attraction_Characteristics_Pessimistic_TurnOff--></T>
  <T n="like">363953<!--trait_Attraction_Characteristics_Pessimistic_TurnOn--></T>
  <V n="tooltip" t="enabled">
    <T n="enabled">0xE9432122<!--<b>Pessimistic</b>\n\nSims with this Turn-On are attracted to these Characteristics: Evil, Gloomy, Hates Children, Jealous, or Noncommittal.\n\nAdditional Characteristics:\n• Unflirty <i>(City Living)</i>\n• Macabre <i>(Life & Death)</i>\n• Skeptical <i>(Life & Death)</i>\n• Paranoid <i>(StrangerVille)</i>--></T>
  </V>
  <L n="trait_map">
    <U>
      <T n="key">124879<!--trait_Jealous--></T>
      <T n="value">2</T>
    </U>
    <U>
      <T n="key">132589<!--trait_Unflirty--></T>
      <T n="value">2</T>
    </U>
    <U>
      <T n="key">16833<!--trait_CommitmentIssues--></T>
      <T n="value">2</T>
    </U>
    <U>
      <T n="key">16836<!--trait_Evil--></T>
      <T n="value">2</T>
    </U>
    <U>
      <T n="key">16844<!--trait_HatesChildren--></T>
      <T n="value">2</T>
    </U>
    <U>
      <T n="key">203542<!--trait_Paranoid--></T>
      <T n="value">2</T>
    </U>
    <U>
      <T n="key">379635<!--trait_Macabre--></T>
      <T n="value">2</T>
    </U>
    <U>
      <T n="key">383203<!--trait_Skeptical--></T>
      <T n="value">2</T>
    </U>
    <U>
      <T n="key">9332<!--trait_Gloomy--></T>
      <T n="value">2</T>
    </U>
  </L>
</I>