<?xml version="1.0" encoding="utf-8"?>
<I c="Buff" i="buff" m="buffs.buff" n="buff_Hopscotch_HoppingMad" s="340938">
  <V n="_temporary_commodity_info" t="enabled">
    <U n="enabled">
      <L n="categories">
        <E>Angry_Buffs</E>
      </L>
      <T n="max_duration">60</T>
    </U>
  </V>
  <T n="audio_sting_on_add" p="InGame\Audio\Stings\sting_buff_gain.propx">39b2aa4a:00000000:8af8b916cf64c646</T>
  <T n="audio_sting_on_remove" p="InGame\Audio\Stings\sting_buff_loss.propx">39b2aa4a:00000000:3bf33216a25546ea</T>
  <T n="buff_description">0x7BBFA014<!--If only {0.SimFirstName} were a frog, {0.SimPronounSubjective} could have won. But alas, {0.SimFirstName} is only a Sim.--></T>
  <T n="buff_name">0x1A2468FB<!--Hopping Mad--></T>
  <T n="icon" p="InEP15\UI\Icons\Buffs\buffs_hopscotch_neg.png">2f7d0004:00000000:89181f8750450d6c</T>
  <T n="mood_type">14632<!--Mood_Angry--></T>
  <T n="mood_weight">2</T>
</I>