<?xml version="1.0" encoding="utf-8"?>
<I c="AccountReward" i="account_reward" m="account_rewards.account_reward_tuning" n="accountReward_DecemberEvent_Collection_03" s="427775">
  <T n="category">0xFB8B7498<!--Collection--></T>
  <T n="image" p="InGame\UI\Icons\LiveEvents\DecemberEvent\Rewards\December_collectibleWreath3_large.png">2f7d0004:00000000:d155a9ce30a636e9</T>
  <L n="items">
    <V t="build_buy_item">
      <U n="build_buy_item">
        <T n="item_resource">460672<!--collectRewardWall_EFDec24EVRwreath_set3 (Cozy Freezer Bunny Wreath)--></T>
      </U>
    </V>
    <V t="consumable_item">
      <U n="consumable_item">
        <T n="item_resource">427782<!--loot_LiveEvents_DecemberEvent_Collection_2--></T>
      </U>
    </V>
  </L>
  <T n="location_tip">0x9F4C459E<!--Find this item in your Sim's inventory.--></T>
  <T n="reward_description">0x7B77B40F<!--Bring that sense of playfulness the holidays bring to your decorations by putting up this Freezer Bunny adorned wreath.--></T>
  <T n="reward_name">0x729AEDD6<!--Cozy Freezer Bunny Wreath--></T>
  <T n="reward_thumbnail_image" p="InGame\UI\Icons\LiveEvents\DecemberEvent\ThumbnailsFSI\December_collectibleWreath3_s.png">2f7d0004:00000000:8a29efe87a0c900f</T>
  <V n="reward_timeline_image" t="large_image">
    <T n="large_image" p="InGame\UI\Icons\LiveEvents\DecemberEvent\Thumbnails\December_collectibleWreath3.png">2f7d0004:00000000:2e16b8104fc71589</T>
  </V>
  <T n="small_image" p="InGame\UI\Icons\LiveEvents\DecemberEvent\Thumbnails\December_collectibleWreath3.png">2f7d0004:00000000:2e16b8104fc71589</T>
</I>