<?xml version="1.0" encoding="utf-8"?>
<I c="PremadeSimTemplate" i="sim_template" m="world.premade_sim_template" n="premadeSimTemplate_EP15_TenantApplicants_SingleMom_Teen" s="357217">
  <U n="_sim_creation_info">
    <T n="first_name">0xB362369E<!--Julie--></T>
    <V n="last_name" t="specify_last_name">
      <T n="specify_last_name">0x5B7676E7<!--Brock--></T>
    </V>
    <T n="resource_key" p="InEP15\Sims\SimInfos\TenantSims\tfJulieBrock.siminfo">025ed6f4:00000000:65876601e45dbcf7</T>
  </U>
  <U n="_traits">
    <L n="explicit">
      <T>350825<!--trait_Hidden_NPC_TenantApplicant--></T>
      <T>27916<!--trait_Bookworm--></T>
      <T>9617<!--trait_Perfectionist--></T>
    </L>
    <V n="num_random" t="disabled" />
  </U>
  <V n="primary_aspiration" t="enabled">
    <T n="enabled">25440<!--Track_Knowledge_A--></T>
  </V>
</I>